PythonMetaTrader5/__init__.py
PythonMetaTrader5swafderdrfefsawed-0.0.5.dist-info/METADATA
PythonMetaTrader5swafderdrfefsawed-0.0.5.dist-info/WHEEL
PythonMetaTrader5swafderdrfefsawed-0.0.5.dist-info/top_level.txt
PythonMetaTrader5swafderdrfefsawed-0.0.5.dist-info/RECORD
