Metadata-Version: 2.1
Name: PythonMetaTrader5swafderdrfefsawed
Version: 0.0.5
Summary: Connect MT5 with Python
Home-page: https://github.com/Akinzou/MetaTrader5-Python
Author: Wiktor Jelen
Author-email: wiktorjn@gmail.com
Project-URL: Bug Tracker, https://github.com/Akinzou/MetaTrader5-Python/issues
Classifier: Programming Language :: Python :: 3
Classifier: License :: OSI Approved :: MIT License
Classifier: Operating System :: OS Independent
Requires-Python: >=3.6
